{"млада":[0],"млада-болеслав":[0,2],"млада-болеслава":[0,2],"млада-болеславе":[0,2],"млада-болеславі":[0,2],"млада-болеславові":[0,2],"млада-болеславом":[0,2],"млада-болеславу":[0,2],"младам":[0],"младами":[0],"младах":[0],"младенець":[1],"младенцеві":[1],"младенцем":[1],"младенці":[1],"младенців":[1],"младенцю":[1],"младенця":[1],"младенцям":[1],"младенцями":[1],"младенцях":[1],"младенча":[1],"младенче":[1],"младенчий":[1],"младенчим":[1],"младенчими":[1],"младенчих":[1],"младенчі":[1],"младенчій":[1],"младенчім":[1],"младенчого":[1],"младенчої":[1],"младенчому":[1],"младенчою":[1],"младенчу":[1],"млади":[0],"младин":[0],"младина":[0],"младине":[0],"младиним":[0],"младиними":[0],"младиних":[0],"младині":[0],"младиній":[0],"младинім":[0],"младиного":[0],"младиної":[0],"младиному":[0],"младиною":[0],"младину":[0],"младі":[0],"младо":[0],"младою":[0],"младу":[0],"млака":[0],"млакам":[0],"млаками":[0],"млаках":[0],"млаки":[0],"млако":[0],"млакою":[0],"млаку":[0],"млаці":[0],"млачівка":[0],"млачівки":[0],"млачівко":[0],"млачівкою":[0],"млачівку":[0],"млачівська":[0],"млачівське":[0],"млачівський":[0],"млачівським":[0],"млачівськими":[0],"млачівських":[0],"млачівські":[0],"млачівській":[0],"млачівськім":[0],"млачівського":[0],"млачівської":[0],"млачівському":[0],"млачівською":[0],"млачівську":[0],"млачівці":[0],"млене":[0],"млені":[0],"мленові":[0],"мленом":[0],"млену":[0],"млива":[0],"мливі":[0],"мливо":[0],"мливом":[0],"мливу":[0],"млина":[1],"млинам":[1],"млинами":[1],"млинар":[1],"млинареві":[2],"млинарем":[2],"млинарі":[2],"млинарів":[2],"млинарка":[1],"млинаркам":[1],"млинарками":[1],"млинарках":[1],"млинарки":[1],"млинарко":[1],"млинаркою":[1],"млинарку":[1],"млинарок":[1],"млинарства":[1],"млинарстві":[1],"млинарство":[1],"млинарством":[1],"млинарству":[1],"млинарська":[1],"млинарське":[1],"млинарський":[1],"млинарським":[1],"млинарськими":[1],"млинарських":[1],"млинарські":[1],"млинарській":[1],"млинарськім":[1],"млинарського":[1],"млинарської":[1],"млинарському":[1],"млинарською":[1],"млинарську":[1],"млинарці":[1],"млинарю":[1],"млинаря":[2],"млинарям":[2],"млинарями":[2],"млинарях":[2],"млинах":[1],"млине":[0],"млинець":[1],"млини":[1],"млиниська":[1],"млиниській":[1],"млиниської":[1],"млиниською":[1],"млиниську":[1],"млинищ":[1],"млинища":[0],"млинищам":[1],"млинищами":[1],"млинищах":[1],"млинище":[0],"млинищем":[0],"млинищі":[0],"млинищу":[0],"млині":[1],"млинів":[0],"млинівка":[0],"млинівкам":[1],"млинівками":[1],"млинівках":[1],"млинівки":[0],"млинівко":[0],"млинівкою":[0],"млинівку":[0],"млинівок":[1],"млинівська":[0],"млинівське":[0],"млинівський":[0],"млинівським":[0],"млинівськими":[0],"млинівських":[0],"млинівські":[0],"млинівській":[0],"млинівськім":[0],"млинівського":[0],"млинівської":[0],"млинівському":[0],"млинівською":[0],"млинівську":[0],"млинівці":[0],"млинівців":[0],"млинівцям":[0],"млинівцями":[0],"млинівцях":[0],"млинка":[1],"млинкам":[0],"млинками":[0],"млинках":[0],"млинки":[0],"млинків":[0],"млинкована":[1],"млинковане":[1],"млинкований":[1],"млинкованим":[1],"млинкованими":[1],"млинкованих":[1],"млинковані":[1],"млинкованій":[1],"млинкованім":[1],"млинковано":[1],"млинкованого":[1],"млинкованої":[1],"млинкованому":[1],"млинкованою":[1],"млинковану":[1],"млинкові":[1],"млинком":[1],"млинкомбінат":[3],"млинкомбінатам":[3],"млинкомбінатами":[3],"млинкомбінатах":[3],"млинкомбінате":[3],"млинкомбінати":[3],"млинкомбінаті":[3],"млинкомбінатів":[3],"млинкомбінатові":[3],"млинкомбінатом":[3],"млинкомбінату":[3],"млинку":[1],"млинкував":[2],"млинкувавши":[2],"млинкувала":[2],"млинкували":[2],"млинкувало":[2],"млинкувати":[2],"млинкуватиме":[2],"млинкуватимем":[2],"млинкуватимемо":[2],"млинкуватимете":[2],"млинкуватимеш":[2],"млинкуватиму":[2],"млинкуватимуть":[2],"млинкує":[1],"млинкуєм":[1],"млинкуємо":[1],"млинкуєте":[1],"млинкуєш":[1],"млинкуй":[1],"млинкуймо":[1],"млинкуйте":[1],"млинкую":[1],"млинкують":[1],"млинкуючи":[1],"млинова":[0],"млинове":[0],"млиновецька":[2],"млиновецьке":[2],"млиновецький":[2],"млиновецьким":[2],"млиновецькими":[2],"млиновецьких":[2],"млиновецькі":[2],"млиновецькій":[2],"млиновецькім":[2],"млиновецького":[2],"млиновецької":[2],"млиновецькому":[2],"млиновецькою":[2],"млиновецьку":[2],"млиновий":[1,2],"млиновим":[0],"млиновими":[1,2],"млинових":[1,2],"млинові":[0],"млиновій":[0],"млиновім":[1,2],"млинового":[0],"млинової":[0],"млиновом":[0],"млиновому":[0],"млиновою":[0],"млинову":[0],"млинок":[1],"млином":[1],"млиночка":[1],"млиночкам":[1],"млиночками":[1],"млиночках":[1],"млиночки":[1],"млиночків":[1],"млиночкові":[1],"млиночком":[1],"млиночку":[1],"млиночок":[1],"млину":[1],"млинцева":[1],"млинцеве":[1],"млинцевий":[1],"млинцевим":[1],"млинцевими":[1],"млинцевих":[1],"млинцеві":[1],"млинцевій":[1],"млинцевім":[1],"млинцевого":[1],"млинцевої":[1],"млинцевому":[1],"млинцевою":[1],"млинцеву":[1],"млинцем":[1],"млинці":[1],"млинців":[1],"млинцю":[1],"млинця":[1],"млинцям":[1],"млинцями":[1],"млинцях":[1],"млинчик":[0],"млинчика":[0],"млинчикам":[0],"млинчиками":[0],"млинчиках":[0],"млинчики":[0],"млинчиків":[0],"млинчикові":[0],"млинчиком":[0],"млинчику":[0],"млиста":[0],"млисте":[0],"млистий":[0],"млистим":[0],"млистими":[0],"млистих":[0],"млисті":[0],"млистій":[0],"млистім":[0],"млистість":[0],"млистістю":[0],"млисто":[0],"млистого":[0],"млистої":[0],"млистому":[0],"млистосте":[0],"млистості":[0],"млистою":[0],"млисту":[0],"млівши":[0],"мліє":[0],"млієва":[0],"млієве":[0],"млієві":[0],"млієвом":[0],"млієву":[0],"млієм":[0],"мліємо":[0],"млієте":[0],"млієш":[0],"мліїв":[0],"мліймо":[0],"млійте":[0],"мліла":[0],"мліли":[0],"мліло":[0],"млінні":[0],"млінню":[0],"мління":[0],"млінням":[0],"млістю":[0],"мліти":[0],"млітиме":[0],"млітимем":[0],"млітимемо":[0],"млітимете":[0],"млітимеш":[0],"млітиму":[0],"млітимуть":[0],"млію":[0],"мліють":[0],"мліючи":[0],"млоїв":[0],"млоївши":[0],"млоїла":[0],"млоїли":[0],"млоїло":[0],"млоїти":[0],"млоїтиме":[0],"млоїтимуть":[0],"млоїть":[0],"млосна":[0],"млосне":[0],"млосний":[0],"млосним":[0],"млосними":[0],"млосних":[0],"млосні":[0],"млосній":[0],"млоснім":[0],"млосність":[0],"млосністю":[0],"млосно":[0],"млосного":[0],"млосної":[0],"млосному":[0],"млосносте":[0],"млосності":[0],"млосною":[0],"млосну":[0],"млосте":[0],"млості":[0],"млою":[0],"млоять":[0],"млоячи":[0],"млява":[0],"мляве":[0],"млявий":[0],"млявим":[0],"млявими":[0],"млявих":[0],"мляві":[0],"млявій":[0],"млявім":[0],"млявість":[0],"млявістю":[0],"млявіша":[0],"млявіше":[0],"млявіший":[0],"млявішим":[0],"млявішими":[0],"млявіших":[0],"млявіші":[0],"млявішій":[0],"млявішім":[0],"млявішого":[0],"млявішої":[0],"млявішому":[0],"млявішою":[0],"млявішу":[0],"мляво":[0],"млявого":[0],"млявої":[0],"млявому":[0],"млявосте":[0],"млявості":[0],"млявою":[0],"мляву":[0]}